Workbook

Sheet Sheet1
A3: Row Labels | B3: Sum of Profit
A4: Apr-2024 | B4: 4322.61
A5: Apr-2025 | B5: 10237.88
A6: Aug-2024 | B6: 7976.39
A7: Dec-2024 | B7: 10480.9
A8: Feb-2024 | B8: 9234.03
A9: Feb-2025 | B9: 7308.92
A10: Jan-2024 | B10: 6054.28
A11: Jan-2025 | B11: 7409.78
A12: Jul-2024 | B12: 8441.19
A13: Jun-2024 | B13: 11775.91
A14: Mar-2024 | B14: 7448.97
A15: Mar-2025 | B15: 10348.18
... A21: Grand Total | B21: 133570.4

Sheet Raw_Data
A1: i | B1: Order_Date | C1: Customer_Name | D1: Country | E1: Product | F1: Category | G1: Quantity | H1: Unit_Price | I1: Total_Sales | J1: Shipping_Cost | K1: Profit | L1: Ship_Mode | M1: Order_Priority | N1: Region_Code | O1: unit cost | P1: COGS | Q1: Profit Margin | R1: Column1
A2: ORD_2025_0001 | B2: Jan-2025 | C2: Smith, Emily | D2: Usa | E2: Travel Backpack | F2: Accessories | G2: 20 | H2: 55.22 | I2: 1104.4 | J2: 49.36 | K2: 355.04 | L2: Land | M2: Low | N2: NA | O2: =_xlfn.XLOOKUP(E2,[1]Products!$B$2:$B$11,[1]Products!$F$2:$F$11) -> 35 | P2: =G2*O2 -> 700 | Q2: =K2/I2 -> 0.32147773 | R2: =MONTH(Table1[[#This Row],[Order_Date]]) -> 1 | S2: =_xlfn.TEXTJOIN(" ",TRUE,N2,L2) -> NA Land
A3: ORD_2025_0002 | B3: Feb-2025 | C3: Brown, Laura | D3: Uk | E3: Leather Wallet | F3: Accessories | G3: 33 | H3: 32.03 | I3: 1056.99 | J3: 59.59 | K3: 403.4 | L3: Sea | M3: Medium | N3: EU | O3: =_xlfn.XLOOKUP(E3,[1]Products!$B$2:$B$11,[1]Products!$F$2:$F$11) -> 18 | P3: =G3*O3 -> 594 | Q3: =K3/I3 -> 0.38164978 | R3: =MONTH(Table1[[#This Row],[Order_Date]]) -> 2
A4: ORD_2025_0003 | B4: Apr-2024 | C4: Davis, John | D4: Italy | E4: Leather Wallet | F4: Accessories | G4: 34 | H4: 28.48 | I4: 968.32 | J4: 73.95 | K4: 282.37 | L4: Land | M4: High | N4: EU | O4: =_xlfn.XLOOKUP(E4,[1]Products!$B$2:$B$11,[1]Products!$F$2:$F$11) -> 18 | P4: =G4*O4 -> 612 | Q4: =K4/I4 -> 0.29160815 | R4: =MONTH(Table1[[#This Row],[Order_Date]]) -> 4
A5: ORD_2025_0004 | B5: Oct-2024 | C5: Miller, Daniel | D5: Brazil | E5: Bluetooth Speaker | F5: Electronics | G5: 6 | H5: 56.36 | I5: 338.16 | J5: 11.39 | K5: 134.77 | L5: Air | M5: Medium | N5: SA | O5: =_xlfn.XLOOKUP(E5,[1]Products!$B$2:$B$11,[1]Products!$F$2:$F$11) -> 32 | P5: =G5*O5 -> 192 | Q5: =K5/I5 -> 0.39853915 | R5: =MONTH(Table1[[#This Row],[Order_Date]]) -> 10
A6: ORD_2025_0005 | B6: Feb-2025 | C6: Johnson, Emma | D6: Canada | E6: Denim Jacket | F6: Apparel | G6: 17 | H6: 69.22 | I6: 1176.74 | J6: 65.94 | K6: 430.8 | L6: Sea | M6: Low | N6: NA | O6: =_xlfn.XLOOKUP(E6,[1]Products!$B$2:$B$11,[1]Products!$F$2:$F$11) -> 40 | P6: =G6*O6 -> 680 | Q6: =K6/I6 -> 0.36609616 | R6: =MONTH(Table1[[#This Row],[Order_Date]]) -> 2
A7: ORD_2025_0006 | B7: Feb-2025 | C7: Johnson, Michael | D7: Mexico | E7: Wireless Mouse | F7: Electronics | G7: 13 | H7: 27.94 | I7: 363.22 | J7: 15.36 | K7: 87.86 | L7: Sea | M7: Low | N7: NA | O7: =_xlfn.XLOOKUP(E7,[1]Products!$B$2:$B$11,[1]Products!$F$2:$F$11) -> 20 | P7: =G7*O7 -> 260 | Q7: =K7/I7 -> 0.24189197 | R7: =MONTH(Table1[[#This Row],[Order_Date]]) -> 2
A8: ORD_2025_0007 | B8: Jun-2024 | C8: Hernandez, Emma | D8: Uk | E8: Glass Bowl Set | F8: Home Decor | G8: 3 | H8: 31.52 | I8: 94.56 | J8: 6.98 | K8: 20.08 | L8: Land | M8: High | N8: EU | O8: =_xlfn.XLOOKUP(E8,[1]Products!$B$2:$B$11,[1]Products!$F$2:$F$11) -> 22.5 | P8: =G8*O8 -> 67.5 | Q8: =K8/I8 -> 0.21235195 | R8: =MONTH(Table1[[#This Row],[Order_Date]]) -> 6
A9: ORD_2025_0008 | B9: May-2025 | C9: Miller, John | D9: China | E9: Cotton Bedsheet | F9: Textiles | G9: 14 | H9: 30.71 | I9: 429.94 | J9: 13.03 | K9: 66.91 | L9: Sea | M9: Low | N9: AS | O9: =_xlfn.XLOOKUP(E9,[1]Products!$B$2:$B$11,[1]Products!$F$2:$F$11) -> 25 | P9: =G9*O9 -> 350 | Q9: =K9/I9 -> 0.15562637 | R9: =MONTH(Table1[[#This Row],[Order_Date]]) -> 5
A10: ORD_2025_0009 | B10: Sep-2024 | C10: Davis, John | D10: Usa | E10: Ceramic Vase | F10: Home Decor | G10: 47 | H10: 24.47 | I10: 1150.09 | J10: 61.3 | K10: 360.29 | L10: Sea | M10: Low | N10: NA | O10: =_xlfn.XLOOKUP(E10,[1]Products!$B$2:$B$11,[1]Products!$F$2:$F$11) -> 15.5 | P10: =G10*O10 -> 728.5 | Q10: =K10/I10 -> 0.31327114 | R10: =MONTH(Table1[[#This Row],[Order_Date]]) -> 9
A11: ORD_2025_0010 | B11: Aug-2024 | C11: Martinez, Laura | D11: Italy | E11: LED Lamp | F11: Electronics | G11: 27 | H11: 18.98 | I11: 512.46 | J11: 28.89 | K11: 139.32 | L11: Sea | M11: High | N11: EU | O11: =_xlfn.XLOOKUP(E11,[1]Products!$B$2:$B$11,[1]Products!$F$2:$F$11) -> 12.75 | P11: =G11*O11 -> 344.25 | Q11: =K11/I11 -> 0.27186512 | R11: =MONTH(Table1[[#This Row],[Order_Date]]) -> 8
A12: ORD_2025_0011 | B12: Apr-2025 | C12: Martinez, James | D12: China | E12: Travel Backpack | F12: Accessories | G12: 32 | H12: 57.84 | I12: 1850.88 | J12: 55.15 | K12: 675.73 | L12: Land | M12: Low | N12: AS | O12: =_xlfn.XLOOKUP(E12,[1]Products!$B$2:$B$11,[1]Products!$F$2:$F$11) -> 35 | P12: =G12*O12 -> 1120 | Q12: =K12/I12 -> 0.3650858 | R12: =MONTH(Table1[[#This Row],[Order_Date]]) -> 4
A13: ORD_2025_0012 | B13: Dec-2024 | C13: Davis, James | D13: Canada | E13: Denim Jacket | F13: Apparel | G13: 49 | H13: 58.77 | I13: 2879.73 | J13: 140.29 | K13: 779.44 | L13: Air | M13: High | N13: NA | O13: =_xlfn.XLOOKUP(E13,[1]Products!$B$2:$B$11,[1]Products!$F$2:$F$11) -> 40 | P13: =G13*O13 -> 1960 | Q13: =K13/I13 -> 0.27066426 | R13: =MONTH(Table1[[#This Row],[Order_Date]]) -> 12
A14: ORD_2025_0013 | B14: Sep-2024 | C14: Martinez, James | D14: Singapore | E14: Travel Backpack | F14: Accessories | G14: 43 | H14: 56.92 | I14: 2447.56 | J14: 140.4 | K14: 802.16 | L14: Land | M14: Medium | N14: AS | O14: =_xlfn.XLOOKUP(E14,[1]Products!$B$2:$B$11,[1]Products!$F$2:$F$11) -> 35 | P14: =G14*O14 -> 1505 | Q14: =K14/I14 -> 0.32773865 | R14: =MONTH(Table1[[#This Row],[Order_Date]]) -> 9
... A501: ORD_2025_0500 | B501: Jul-2024 | C501: Hernandez, Michael | D501: Uk | E501: Ceramic Vase | F501: Home Decor | G501: 7 | H501: 24.61 | I501: 172.27 | J501: 9.64 | K501: 54.13 | L501: Air | M501: High | N501: EU | O501: =_xlfn.XLOOKUP(E501,[1]Products!$B$2:$B$11,[1]Products!$F$2:$F$11) -> 15.5 | P501: =G501*O501 -> 108.5 | Q501: =K501/I501 -> 0.31421606 | R501: =MONTH(Table1[[#This Row],[Order_Date]]) -> 7

Sheet Clean_Data
A1: first name | B1: last name | C1: Cust Code
A2: =TRIM(MID(Raw_Data!C2,FIND(",",Raw_Data!C2)+1,LEN(Raw_Data!C2))) -> Emily | B2: =LEFT(Raw_Data!C2,FIND(",",Raw_Data!C2)-1) -> Smith | C2: =LEFT(A2,2) & LEFT(B2,2) & ROW() -> EmSm2
A3: =TRIM(MID(Raw_Data!C3,FIND(",",Raw_Data!C3)+1,LEN(Raw_Data!C3))) -> Laura | B3: =LEFT(Raw_Data!C3,FIND(",",Raw_Data!C3)-1) -> Brown | C3: =LEFT(A3,2) & LEFT(B3,2) & ROW() -> LaBr3
A4: =TRIM(MID(Raw_Data!C4,FIND(",",Raw_Data!C4)+1,LEN(Raw_Data!C4))) -> John | B4: =LEFT(Raw_Data!C4,FIND(",",Raw_Data!C4)-1) -> Davis | C4: =LEFT(A4,2) & LEFT(B4,2) & ROW() -> JoDa4
A5: =TRIM(MID(Raw_Data!C5,FIND(",",Raw_Data!C5)+1,LEN(Raw_Data!C5))) -> Daniel | B5: =LEFT(Raw_Data!C5,FIND(",",Raw_Data!C5)-1) -> Miller | C5: =LEFT(A5,2) & LEFT(B5,2) & ROW() -> DaMi5
A6: =TRIM(MID(Raw_Data!C6,FIND(",",Raw_Data!C6)+1,LEN(Raw_Data!C6))) -> Emma | B6: =LEFT(Raw_Data!C6,FIND(",",Raw_Data!C6)-1) -> Johnson | C6: =LEFT(A6,2) & LEFT(B6,2) & ROW() -> EmJo6
A7: =TRIM(MID(Raw_Data!C7,FIND(",",Raw_Data!C7)+1,LEN(Raw_Data!C7))) -> Michael | B7: =LEFT(Raw_Data!C7,FIND(",",Raw_Data!C7)-1) -> Johnson | C7: =LEFT(A7,2) & LEFT(B7,2) & ROW() -> MiJo7
A8: =TRIM(MID(Raw_Data!C8,FIND(",",Raw_Data!C8)+1,LEN(Raw_Data!C8))) -> Emma | B8: =LEFT(Raw_Data!C8,FIND(",",Raw_Data!C8)-1) -> Hernandez | C8: =LEFT(A8,2) & LEFT(B8,2) & ROW() -> EmHe8
A9: =TRIM(MID(Raw_Data!C9,FIND(",",Raw_Data!C9)+1,LEN(Raw_Data!C9))) -> John | B9: =LEFT(Raw_Data!C9,FIND(",",Raw_Data!C9)-1) -> Miller | C9: =LEFT(A9,2) & LEFT(B9,2) & ROW() -> JoMi9
A10: =TRIM(MID(Raw_Data!C10,FIND(",",Raw_Data!C10)+1,LEN(Raw_Data!C10))) -> John | B10: =LEFT(Raw_Data!C10,FIND(",",Raw_Data!C10)-1) -> Davis | C10: =LEFT(A10,2) & LEFT(B10,2) & ROW() -> JoDa10
A11: =TRIM(MID(Raw_Data!C11,FIND(",",Raw_Data!C11)+1,LEN(Raw_Data!C11))) -> Laura | B11: =LEFT(Raw_Data!C11,FIND(",",Raw_Data!C11)-1) -> Martinez | C11: =LEFT(A11,2) & LEFT(B11,2) & ROW() -> LaMa11
A12: =TRIM(MID(Raw_Data!C12,FIND(",",Raw_Data!C12)+1,LEN(Raw_Data!C12))) -> James | B12: =LEFT(Raw_Data!C12,FIND(",",Raw_Data!C12)-1) -> Martinez | C12: =LEFT(A12,2) & LEFT(B12,2) & ROW() -> JaMa12
A13: =TRIM(MID(Raw_Data!C13,FIND(",",Raw_Data!C13)+1,LEN(Raw_Data!C13))) -> James | B13: =LEFT(Raw_Data!C13,FIND(",",Raw_Data!C13)-1) -> Davis | C13: =LEFT(A13,2) & LEFT(B13,2) & ROW() -> JaDa13
... A242: =TRIM(MID(Raw_Data!C242,FIND(",",Raw_Data!C242)+1,LEN(Raw_Data!C242))) -> John | B242: =LEFT(Raw_Data!C242,FIND(",",Raw_Data!C242)-1) -> Brown | C242: =LEFT(A242,2) & LEFT(B242,2) & ROW() -> JoBr242

Sheet Summary_Tables
