Workbook

Sheet Sheet3
A3: Row Labels | B3: Sum of Total_Sales | C3: Sum of Profit
A4: Apr-2024 | B4: 14076.35 | C4: 4322.61
A5: Apr-2025 | B5: 36539.25 | C5: 10237.88
A6: Aug-2024 | B6: 28579.07 | C6: 7976.39
A7: Dec-2024 | B7: 39119.29 | C7: 10480.9
A8: Feb-2024 | B8: 29912 | C8: 9234.03
A9: Feb-2025 | B9: 25532.23 | C9: 7308.92
A10: Jan-2024 | B10: 23642.31 | C10: 6054.28
A11: Jan-2025 | B11: 25063.02 | C11: 7409.78
A12: Jul-2024 | B12: 30288.91 | C12: 8441.19
A13: Jun-2024 | B13: 38692.6 | C13: 11775.91
A14: Mar-2024 | B14: 27450.58 | C14: 7448.97
A15: Mar-2025 | B15: 32154.88 | C15: 10348.18
... A20: Sep-2024 | B20: 31738.73 | C20: 8387.18
A21: (blank)
A22: Grand Total | B22: 474704.62 | C22: 133528.36
A26: Sum of Total_Sales | B26: Column Labels
A27: Row Labels | B27: AF | C27: AS | D27: EU | E27: NA | F27: OC | G27: SA | H27: Grand Total
A28: Accessories | B28: 6956.41 | C28: 33225.64 | D28: 30642.08 | E28: 24079.71 | F28: 6810.06 | G28: 8480.99 | H28: 110194.89
A29: Apparel | B29: 6721.25 | C29: 30263.43 | D29: 11433.35 | E29: 9625.97 | F29: 12174.14 | G29: 2134.23 | H29: 72352.37
A30: Electronics | B30: 7452.94 | C30: 34174.13 | D30: 25086.15 | E30: 22495.01 | F30: 8892.01 | G30: 16927.67 | H30: 115027.91
A31: Home Decor | B31: 8364.44 | C31: 51860.89 | D31: 33685.94 | E31: 26924.32 | F31: 6972.93 | G31: 2088.92 | H31: 129897.44
A32: Textiles | C32: 21644.31 | D32: 14367.1 | E32: 3820.06 | F32: 2168.32 | G32: 5232.22 | H32: 47232.01
A33: Grand Total | B33: 29495.04 | C33: 171168.4 | D33: 115214.62 | E33: 86945.07 | F33: 37017.46 | G33: 34864.03 | H33: 474704.62

Sheet Global_trade
A1: i | B1: Order_Date | C1: Customer_Name | D1: Country | E1: Product | F1: Category | G1: Quantity | H1: Unit_Price | I1: Total_Sales | J1: Shipping_Cost | K1: Profit | L1: Ship_Mode | M1: Order_Priority | N1: Region_Code | O1: Clean
A2: ORD_2025_0001 | B2: Jan-2025 | C2: Smith, Emily | D2: Usa | E2: Travel Backpack | F2: Accessories | G2: 20 | H2: 55.22 | I2: 1104.4 | J2: 49.36 | K2: 355.04 | L2: Land | M2: Low | N2: NA | O2: =DATE(YEAR(Table1[[#This Row],[Order_Date]]), MONTH(Table1[[#This Row],[Order_Date]]), 1) -> 45658
A3: ORD_2025_0002 | B3: Feb-2025 | C3: Brown, Laura | D3: Uk | E3: Leather Wallet | F3: Accessories | G3: 33 | H3: 32.03 | I3: 1056.99 | J3: 59.59 | K3: 403.4 | L3: Sea | M3: Medium | N3: EU | O3: =DATE(YEAR(Table1[[#This Row],[Order_Date]]), MONTH(Table1[[#This Row],[Order_Date]]), 1) -> 45689
A4: ORD_2025_0003 | B4: Apr-2024 | C4: Davis, John | D4: Italy | E4: Leather Wallet | F4: Accessories | G4: 34 | H4: 28.48 | I4: 968.32 | J4: 73.95 | K4: 282.37 | L4: Land | M4: High | N4: EU | O4: =DATE(YEAR(Table1[[#This Row],[Order_Date]]), MONTH(Table1[[#This Row],[Order_Date]]), 1) -> 45383
A5: ORD_2025_0004 | B5: Oct-2024 | C5: Miller, Daniel | D5: Brazil | E5: Bluetooth Speaker | F5: Electronics | G5: 6 | H5: 56.36 | I5: 338.16 | J5: 11.39 | K5: 134.77 | L5: Air | M5: Medium | N5: SA | O5: =DATE(YEAR(Table1[[#This Row],[Order_Date]]), MONTH(Table1[[#This Row],[Order_Date]]), 1) -> 45566
A6: ORD_2025_0005 | B6: Feb-2025 | C6: Johnson, Emma | D6: Canada | E6: Denim Jacket | F6: Apparel | G6: 17 | H6: 69.22 | I6: 1176.74 | J6: 65.94 | K6: 430.8 | L6: Sea | M6: Low | N6: NA | O6: =DATE(YEAR(Table1[[#This Row],[Order_Date]]), MONTH(Table1[[#This Row],[Order_Date]]), 1) -> 45689
A7: ORD_2025_0006 | B7: Feb-2025 | C7: Johnson, Michael | D7: Mexico | E7: Wireless Mouse | F7: Electronics | G7: 13 | H7: 27.94 | I7: 363.22 | J7: 15.36 | K7: 87.86 | L7: Sea | M7: Low | N7: NA | O7: =DATE(YEAR(Table1[[#This Row],[Order_Date]]), MONTH(Table1[[#This Row],[Order_Date]]), 1) -> 45689
A8: ORD_2025_0007 | B8: Jun-2024 | C8: Hernandez, Emma | D8: Uk | E8: Glass Bowl Set | F8: Home Decor | G8: 3 | H8: 31.52 | I8: 94.56 | J8: 6.98 | K8: 20.08 | L8: Land | M8: High | N8: EU | O8: =DATE(YEAR(Table1[[#This Row],[Order_Date]]), MONTH(Table1[[#This Row],[Order_Date]]), 1) -> 45444
A9: ORD_2025_0008 | B9: May-2025 | C9: Miller, John | D9: China | E9: Cotton Bedsheet | F9: Textiles | G9: 14 | H9: 30.71 | I9: 429.94 | J9: 13.03 | K9: 66.91 | L9: Sea | M9: Low | N9: AS | O9: =DATE(YEAR(Table1[[#This Row],[Order_Date]]), MONTH(Table1[[#This Row],[Order_Date]]), 1) -> 45778
A10: ORD_2025_0009 | B10: Sep-2024 | C10: Davis, John | D10: Usa | E10: Ceramic Vase | F10: Home Decor | G10: 47 | H10: 24.47 | I10: 1150.09 | J10: 61.3 | K10: 360.29 | L10: Sea | M10: Low | N10: NA | O10: =DATE(YEAR(Table1[[#This Row],[Order_Date]]), MONTH(Table1[[#This Row],[Order_Date]]), 1) -> 45536
A11: ORD_2025_0010 | B11: Aug-2024 | C11: Martinez, Laura | D11: Italy | E11: LED Lamp | F11: Electronics | G11: 27 | H11: 18.98 | I11: 512.46 | J11: 28.89 | K11: 139.32 | L11: Sea | M11: High | N11: EU | O11: =DATE(YEAR(Table1[[#This Row],[Order_Date]]), MONTH(Table1[[#This Row],[Order_Date]]), 1) -> 45505
A12: ORD_2025_0011 | B12: Apr-2025 | C12: Martinez, James | D12: China | E12: Travel Backpack | F12: Accessories | G12: 32 | H12: 57.84 | I12: 1850.88 | J12: 55.15 | K12: 675.73 | L12: Land | M12: Low | N12: AS | O12: =DATE(YEAR(Table1[[#This Row],[Order_Date]]), MONTH(Table1[[#This Row],[Order_Date]]), 1) -> 45748
A13: ORD_2025_0012 | B13: Dec-2024 | C13: Davis, James | D13: Canada | E13: Denim Jacket | F13: Apparel | G13: 49 | H13: 58.77 | I13: 2879.73 | J13: 140.29 | K13: 779.44 | L13: Air | M13: High | N13: NA | O13: =DATE(YEAR(Table1[[#This Row],[Order_Date]]), MONTH(Table1[[#This Row],[Order_Date]]), 1) -> 45627
... A501: ORD_2025_0500 | B501: Jul-2024 | C501: Hernandez, Michael | D501: Uk | E501: Ceramic Vase | F501: Home Decor | G501: 7 | H501: 24.61 | I501: 172.27 | J501: 9.64 | K501: 54.13 | L501: Air | M501: High | N501: EU | O501: =DATE(YEAR(Table1[[#This Row],[Order_Date]]), MONTH(Table1[[#This Row],[Order_Date]]), 1) -> 45474

Sheet Product_Master
A1: Product_ID | B1: Product | C1: Category | D1: Supplier | E1: Origin_Country | F1: Unit_Cost
A2: P1001 | B2: Bluetooth Speaker | C2: Electronics | D2: AudioTech Ltd. | E2: China | F2: 32
A3: P1002 | B3: Ceramic Vase | C3: Home Decor | D3: Artisans Co. | E3: India | F3: 15.5 | I3: Origin_Country | J3: Supplier
A4: P1003 | B4: Leather Wallet | C4: Accessories | D4: CraftLine | E4: Italy | F4: 18 | I4: China | J4: =INDEX(A2:F11,MATCH(I4,E2:E11,0),4) -> AudioTech Ltd.
A5: P1004 | B5: LED Lamp | C5: Electronics | D5: BrightHome | E5: Vietnam | F5: 12.75
A6: P1005 | B6: Cotton Bedsheet | C6: Textiles | D6: SoftWeave | E6: Turkey | F6: 25
A7: P1006 | B7: Wireless Mouse | C7: Electronics | D7: ClickTech | E7: China | F7: 20
A8: P1007 | B8: Glass Bowl Set | C8: Home Decor | D8: ClearCraft | E8: India | F8: 22.5
A9: P1008 | B9: Travel Backpack | C9: Accessories | D9: CarryPro | E9: Vietnam | F9: 35
A10: P1009 | B10: Table Lamp | C10: Home Decor | D10: BrightHome | E10: India | F10: 28
A11: P1010 | B11: Denim Jacket | C11: Apparel | D11: BlueWear | E11: Bangladesh | F11: 40

Sheet Performance
A1: Region_Code | B1: Month | C1: Total_Sales | D1: Total_Profit | E1: Shipments | F1: Returns
A2: AF | B2: 2024-02 | C2: 3778.57 | D2: 1212.12 | E2: 3 | F2: 5
A3: AF | B3: 2024-03 | C3: 3519.18 | D3: 910.68 | E3: 2 | F3: 3
A4: AF | B4: 2024-04 | C4: 1765.51 | D4: 530.96 | E4: 2 | F4: 4
A5: AF | B5: 2024-06 | C5: 4768.72 | D5: 1717.12 | E5: 3 | F5: 7
A6: AF | B6: 2024-07 | C6: 751.14 | D6: 168.93 | E6: 4 | F6: 8
A7: AF | B7: 2024-09 | C7: 2704.41 | D7: 772.61 | E7: 3 | F7: 5
A8: AF | B8: 2024-10 | C8: 908.84 | D8: 264.43 | E8: 2 | F8: 6
A9: AF | B9: 2024-11 | C9: 794.82 | D9: 255.37 | E9: 1 | F9: 7
A10: AF | B10: 2024-12 | C10: 1882.75 | D10: 346.8 | E10: 4 | F10: 3
A11: AF | B11: 2025-01 | C11: 3269.37 | D11: 1085.41 | E11: 2 | F11: 2
A12: AF | B12: 2025-02 | C12: 412.62 | D12: 155.44 | E12: 1 | F12: 8
A13: AF | B13: 2025-03 | C13: 2964.8 | D13: 920.04 | E13: 4 | F13: 4
... A94: SA | B94: 2025-05 | C94: 1027.68 | D94: 357.73 | E94: 1 | F94: 1

Sheet Region
A1: Region_Code | B1: Region_Name | C1: Continent | D1: Manager
A2: NA | B2: North America | C2: America | D2: James Carter
A3: EU | B3: Europe | C3: Europe | D3: Maria Gomez
A4: AS | B4: Asia | C4: Asia | D4: Li Wei
A5: AF | B5: Africa | C5: Africa | D5: Samuel Okoro
A6: SA | B6: South America | C6: America | D6: Ana Silva
A7: OC | B7: Oceania | C7: Australia | D7: Steve Taylor

Sheet Q2
A1: i | B1: Order_Date | C1: Customer_Name | D1: Country | E1: Product | F1: Category | G1: Quantity | H1: Unit_Price | I1: Total_Sales | J1: Shipping_Cost | K1: Profit | L1: Ship_Mode | M1: Order_Priority | N1: Region_Code | O1: Unit_cost | P1: COGS | Q1: Profit Margin
A2: ORD_2025_0001 | B2: Jan-2025 | C2: Smith, Emily | D2: Usa | E2: Travel Backpack | F2: Accessories | G2: 20 | H2: 55.22 | I2: 1104.4 | J2: 49.36 | K2: 355.04 | L2: Land | M2: Low | N2: NA | O2: =_xlfn.XLOOKUP(E2,Product_Master!$B$2:$B$11,Product_Master!$F$2:$F$11) -> 35 | P2: =G2*O2 -> 700 | Q2: =K2/I2 -> 0.32147773
A3: ORD_2025_0002 | B3: Feb-2025 | C3: Brown, Laura | D3: Uk | E3: Leather Wallet | F3: Accessories | G3: 33 | H3: 32.03 | I3: 1056.99 | J3: 59.59 | K3: 403.4 | L3: Sea | M3: Medium | N3: EU | O3: =_xlfn.XLOOKUP(E3,Product_Master!$B$2:$B$11,Product_Master!$F$2:$F$11) -> 18 | P3: =G3*O3 -> 594 | Q3: =K3/I3 -> 0.38164978
A4: ORD_2025_0003 | B4: Apr-2024 | C4: Davis, John | D4: Italy | E4: Leather Wallet | F4: Accessories | G4: 34 | H4: 28.48 | I4: 968.32 | J4: 73.95 | K4: 282.37 | L4: Land | M4: High | N4: EU | O4: =_xlfn.XLOOKUP(E4,Product_Master!$B$2:$B$11,Product_Master!$F$2:$F$11) -> 18 | P4: =G4*O4 -> 612 | Q4: =K4/I4 -> 0.29160815 | S4: Metric | T4: Value
A5: ORD_2025_0004 | B5: Oct-2024 | C5: Miller, Daniel | D5: Brazil | E5: Bluetooth Speaker | F5: Electronics | G5: 6 | H5: 56.36 | I5: 338.16 | J5: 11.39 | K5: 134.77 | L5: Air | M5: Medium | N5: SA | O5: =_xlfn.XLOOKUP(E5,Product_Master!$B$2:$B$11,Product_Master!$F$2:$F$11) -> 32 | P5: =G5*O5 -> 192 | Q5: =K5/I5 -> 0.39853915 | S5: Average Profit Margin | T5: =AVERAGE(Q2:Q501) -> 0.27267437
A6: ORD_2025_0005 | B6: Feb-2025 | C6: Johnson, Emma | D6: Canada | E6: Denim Jacket | F6: Apparel | G6: 17 | H6: 69.22 | I6: 1176.74 | J6: 65.94 | K6: 430.8 | L6: Sea | M6: Low | N6: NA | O6: =_xlfn.XLOOKUP(E6,Product_Master!$B$2:$B$11,Product_Master!$F$2:$F$11) -> 40 | P6: =G6*O6 -> 680 | Q6: =K6/I6 -> 0.36609616 | S6: Max Profit Margin | T6: =MAX(Q2:Q501) -> 0.42019875
A7: ORD_2025_0006 | B7: Feb-2025 | C7: Johnson, Michael | D7: Mexico | E7: Wireless Mouse | F7: Electronics | G7: 13 | H7: 27.94 | I7: 363.22 | J7: 15.36 | K7: 87.86 | L7: Sea | M7: Low | N7: NA | O7: =_xlfn.XLOOKUP(E7,Product_Master!$B$2:$B$11,Product_Master!$F$2:$F$11) -> 20 | P7: =G7*O7 -> 260 | Q7: =K7/I7 -> 0.24189197 | S7: Min Profit Margin | T7: =MIN(Q2:Q501) -> 0.093578691
A8: ORD_2025_0007 | B8: Jun-2024 | C8: Hernandez, Emma | D8: Uk | E8: Glass Bowl Set | F8: Home Decor | G8: 3 | H8: 31.52 | I8: 94.56 | J8: 6.98 | K8: 20.08 | L8: Land | M8: High | N8: EU | O8: =_xlfn.XLOOKUP(E8,Product_Master!$B$2:$B$11,Product_Master!$F$2:$F$11) -> 22.5 | P8: =G8*O8 -> 67.5 | Q8: =K8/I8 -> 0.21235195
A9: ORD_2025_0008 | B9: May-2025 | C9: Miller, John | D9: China | E9: Cotton Bedsheet | F9: Textiles | G9: 14 | H9: 30.71 | I9: 429.94 | J9: 13.03 | K9: 66.91 | L9: Sea | M9: Low | N9: AS | O9: =_xlfn.XLOOKUP(E9,Product_Master!$B$2:$B$11,Product_Master!$F$2:$F$11) -> 25 | P9: =G9*O9 -> 350 | Q9: =K9/I9 -> 0.15562637
A10: ORD_2025_0009 | B10: Sep-2024 | C10: Davis, John | D10: Usa | E10: Ceramic Vase | F10: Home Decor | G10: 47 | H10: 24.47 | I10: 1150.09 | J10: 61.3 | K10: 360.29 | L10: Sea | M10: Low | N10: NA | O10: =_xlfn.XLOOKUP(E10,Product_Master!$B$2:$B$11,Product_Master!$F$2:$F$11) -> 15.5 | P10: =G10*O10 -> 728.5 | Q10: =K10/I10 -> 0.31327114
A11: ORD_2025_0010 | B11: Aug-2024 | C11: Martinez, Laura | D11: Italy | E11: LED Lamp | F11: Electronics | G11: 27 | H11: 18.98 | I11: 512.46 | J11: 28.89 | K11: 139.32 | L11: Sea | M11: High | N11: EU | O11: =_xlfn.XLOOKUP(E11,Product_Master!$B$2:$B$11,Product_Master!$F$2:$F$11) -> 12.75 | P11: =G11*O11 -> 344.25 | Q11: =K11/I11 -> 0.27186512
A12: ORD_2025_0011 | B12: Apr-2025 | C12: Martinez, James | D12: China | E12: Travel Backpack | F12: Accessories | G12: 32 | H12: 57.84 | I12: 1850.88 | J12: 55.15 | K12: 675.73 | L12: Land | M12: Low | N12: AS | O12: =_xlfn.XLOOKUP(E12,Product_Master!$B$2:$B$11,Product_Master!$F$2:$F$11) -> 35 | P12: =G12*O12 -> 1120 | Q12: =K12/I12 -> 0.3650858
A13: ORD_2025_0012 | B13: Dec-2024 | C13: Davis, James | D13: Canada | E13: Denim Jacket | F13: Apparel | G13: 49 | H13: 58.77 | I13: 2879.73 | J13: 140.29 | K13: 779.44 | L13: Air | M13: High | N13: NA | O13: =_xlfn.XLOOKUP(E13,Product_Master!$B$2:$B$11,Product_Master!$F$2:$F$11) -> 40 | P13: =G13*O13 -> 1960 | Q13: =K13/I13 -> 0.27066426
A14: ORD_2025_0013 | B14: Sep-2024 | C14: Martinez, James | D14: Singapore | E14: Travel Backpack | F14: Accessories | G14: 43 | H14: 56.92 | I14: 2447.56 | J14: 140.4 | K14: 802.16 | L14: Land | M14: Medium | N14: AS | O14: =_xlfn.XLOOKUP(E14,Product_Master!$B$2:$B$11,Product_Master!$F$2:$F$11) -> 35 | P14: =G14*O14 -> 1505 | Q14: =K14/I14 -> 0.32773865
A15: ORD_2025_0014 | B15: Feb-2024 | C15: Smith, Emma | D15: Italy | E15: Cotton Bedsheet | F15: Textiles | G15: 32 | H15: 43.45 | I15: 1390.4 | J15: 30.04 | K15: 560.36 | L15: Land | M15: High | N15: EU | O15: =_xlfn.XLOOKUP(E15,Product_Master!$B$2:$B$11,Product_Master!$F$2:$F$11) -> 25 | P15: =G15*O15 -> 800 | Q15: =K15/I15 -> 0.40302071
A16: ORD_2025_0015 | B16: Mar-2024 | C16: Davis, Sarah | D16: Uae | E16: Cotton Bedsheet | F16: Textiles | G16: 22 | H16: 42.59 | I16: 936.98 | J16: 29.87 | K16: 357.11 | L16: Sea | M16: High | N16: AS | O16: =_xlfn.XLOOKUP(E16,Product_Master!$B$2:$B$11,Product_Master!$F$2:$F$11) -> 25 | P16: =G16*O16 -> 550 | Q16: =K16/I16 -> 0.38112873
A17: ORD_2025_0016 | B17: Sep-2024 | C17: Williams, David | D17: Japan | E17: Wireless Mouse | F17: Electronics | G17: 48 | H17: 25.36 | I17: 1217.28 | J17: 49.68 | K17: 207.6 | L17: Sea | M17: Low | N17: AS | O17: =_xlfn.XLOOKUP(E17,Product_Master!$B$2:$B$11,Product_Master!$F$2:$F$11) -> 20 | P17: =G17*O17 -> 960 | Q17: =K17/I17 -> 0.17054416
A18: ORD_2025_0017 | B18: Aug-2024 | C18: Martinez, James | D18: Uae | E18: Leather Wallet | F18: Accessories | G18: 48 | H18: 30.07 | I18: 1443.36 | J18: 102.31 | K18: 477.05 | L18: Air | M18: Low | N18: AS | O18: =_xlfn.XLOOKUP(E18,Product_Master!$B$2:$B$11,Product_Master!$F$2:$F$11) -> 18 | P18: =G18*O18 -> 864 | Q18: =K18/I18 -> 0.33051352
A19: ORD_2025_0018 | B19: Sep-2024 | C19: Johnson, Michael | D19: Uae | E19: Wireless Mouse | F19: Electronics | G19: 6 | H19: 32.17 | I19: 193.02 | J19: 14.45 | K19: 58.57 | L19: Air | M19: Low | N19: AS | O19: =_xlfn.XLOOKUP(E19,Product_Master!$B$2:$B$11,Product_Master!$F$2:$F$11) -> 20 | P19: =G19*O19 -> 120 | Q19: =K19/I19 -> 0.30344006
... A501: ORD_2025_0500 | B501: 2024-07-14 | C501: Hernandez, Michael | D501: Uk | E501: Ceramic Vase | F501: Home Decor | G501: 7 | H501: 24.61 | I501: 172.27 | J501: 9.64 | K501: 54.13 | L501: Air | M501: High | N501: EU | O501: =_xlfn.XLOOKUP(E501,Product_Master!$B$2:$B$11,Product_Master!$F$2:$F$11) -> 15.5 | P501: =G501*O501 -> 108.5 | Q501: =K501/I501 -> 0.31421606

Sheet Q1
A1: Order_Date | B1: Country | C1: Unit_Price | D1: Total_Sales | E1: Profit
A2: Jan-2025 | B2: Usa | C2: 55.22 | D2: 1104.4 | E2: 355.04
A3: Feb-2025 | B3: Uk | C3: 32.03 | D3: 1056.99 | E3: 403.4
A4: Apr-2024 | B4: Italy | C4: 28.48 | D4: 968.32 | E4: 282.37
A5: Oct-2024 | B5: Brazil | C5: 56.36 | D5: 338.16 | E5: 134.77
A6: Feb-2025 | B6: Canada | C6: 69.22 | D6: 1176.74 | E6: 430.8
A7: Feb-2025 | B7: Mexico | C7: 27.94 | D7: 363.22 | E7: 87.86
A8: Jun-2024 | B8: Uk | C8: 31.52 | D8: 94.56 | E8: 20.08
A9: May-2025 | B9: China | C9: 30.71 | D9: 429.94 | E9: 66.91
A10: Sep-2024 | B10: Usa | C10: 24.47 | D10: 1150.09 | E10: 360.29
A11: Aug-2024 | B11: Italy | C11: 18.98 | D11: 512.46 | E11: 139.32
A12: Apr-2025 | B12: China | C12: 57.84 | D12: 1850.88 | E12: 675.73
A13: Dec-2024 | B13: Canada | C13: 58.77 | D13: 2879.73 | E13: 779.44
... A501: 2024-07-14 | B501: Uk | C501: 24.61 | D501: 172.27 | E501: 54.13

Sheet Q3
A1: Customer Name | B1: First Name | C1: Last Name | D1: Customer Code
A2: Smith, Emily | B2: Smith | C2: Emily | D2: =LEFT(B2,2)&LEFT(C2,2)&ROW() -> SmEm2
A3: Brown, Laura | B3: Brown | C3: Laura | D3: =LEFT(B3,2)&LEFT(C3,2)&ROW() -> BrLa3
A4: Davis, John | B4: Davis | C4: John | D4: =LEFT(B4,2)&LEFT(C4,2)&ROW() -> DaJo4
A5: Miller, Daniel | B5: Miller | C5: Daniel | D5: =LEFT(B5,2)&LEFT(C5,2)&ROW() -> MiDa5
A6: Johnson, Emma | B6: Johnson | C6: Emma | D6: =LEFT(B6,2)&LEFT(C6,2)&ROW() -> JoEm6
A7: Johnson, Michael | B7: Johnson | C7: Michael | D7: =LEFT(B7,2)&LEFT(C7,2)&ROW() -> JoMi7
A8: Hernandez, Emma | B8: Hernandez | C8: Emma | D8: =LEFT(B8,2)&LEFT(C8,2)&ROW() -> HeEm8
A9: Miller, John | B9: Miller | C9: John | D9: =LEFT(B9,2)&LEFT(C9,2)&ROW() -> MiJo9
A10: Davis, John | B10: Davis | C10: John | D10: =LEFT(B10,2)&LEFT(C10,2)&ROW() -> DaJo10
A11: Martinez, Laura | B11: Martinez | C11: Laura | D11: =LEFT(B11,2)&LEFT(C11,2)&ROW() -> MaLa11
A12: Martinez, James | B12: Martinez | C12: James | D12: =LEFT(B12,2)&LEFT(C12,2)&ROW() -> MaJa12
A13: Davis, James | B13: Davis | C13: James | D13: =LEFT(B13,2)&LEFT(C13,2)&ROW() -> DaJa13
... A501: Hernandez, Michael | B501: Hernandez | C501: Michael | D501: =LEFT(B501,2)&LEFT(C501,2)&ROW() -> HeMi501

Sheet Q4
A1: Total_Sales | B1: Profit | C1: Margin | D1: Perform
A2: 1104.4 | B2: 355.04 | C2: =B2/A2 -> 0.32147773 | D2: {=_xlfn.IFS(AND(C2>20%, A2>2000),"Excellent", AND(C2<20%, C2>10%),"Good",TRUE,"BAD")} -> BAD
A3: 1056.99 | B3: 403.4 | C3: =B3/A3 -> 0.38164978 | D3: {=_xlfn.IFS(AND(C3>20%, A3>2000),"Excellent", AND(C3<20%, C3>10%),"Good",TRUE,"BAD")} -> BAD
A4: 968.32 | B4: 282.37 | C4: =B4/A4 -> 0.29160815 | D4: {=_xlfn.IFS(AND(C4>20%, A4>2000),"Excellent", AND(C4<20%, C4>10%),"Good",TRUE,"BAD")} -> BAD
A5: 338.16 | B5: 134.77 | C5: =B5/A5 -> 0.39853915 | D5: {=_xlfn.IFS(AND(C5>20%, A5>2000),"Excellent", AND(C5<20%, C5>10%),"Good",TRUE,"BAD")} -> BAD
A6: 1176.74 | B6: 430.8 | C6: =B6/A6 -> 0.36609616 | D6: {=_xlfn.IFS(AND(C6>20%, A6>2000),"Excellent", AND(C6<20%, C6>10%),"Good",TRUE,"BAD")} -> BAD
A7: 363.22 | B7: 87.86 | C7: =B7/A7 -> 0.24189197 | D7: {=_xlfn.IFS(AND(C7>20%, A7>2000),"Excellent", AND(C7<20%, C7>10%),"Good",TRUE,"BAD")} -> BAD
A8: 94.56 | B8: 20.08 | C8: =B8/A8 -> 0.21235195 | D8: {=_xlfn.IFS(AND(C8>20%, A8>2000),"Excellent", AND(C8<20%, C8>10%),"Good",TRUE,"BAD")} -> BAD
A9: 429.94 | B9: 66.91 | C9: =B9/A9 -> 0.15562637 | D9: {=_xlfn.IFS(AND(C9>20%, A9>2000),"Excellent", AND(C9<20%, C9>10%),"Good",TRUE,"BAD")} -> Good
A10: 1150.09 | B10: 360.29 | C10: =B10/A10 -> 0.31327114 | D10: {=_xlfn.IFS(AND(C10>20%, A10>2000),"Excellent", AND(C10<20%, C10>10%),"Good",TRUE,"BAD")} -> BAD
A11: 512.46 | B11: 139.32 | C11: =B11/A11 -> 0.27186512 | D11: {=_xlfn.IFS(AND(C11>20%, A11>2000),"Excellent", AND(C11<20%, C11>10%),"Good",TRUE,"BAD")} -> BAD
A12: 1850.88 | B12: 675.73 | C12: =B12/A12 -> 0.3650858 | D12: {=_xlfn.IFS(AND(C12>20%, A12>2000),"Excellent", AND(C12<20%, C12>10%),"Good",TRUE,"BAD")} -> BAD
A13: 2879.73 | B13: 779.44 | C13: =B13/A13 -> 0.27066426 | D13: {=_xlfn.IFS(AND(C13>20%, A13>2000),"Excellent", AND(C13<20%, C13>10%),"Good",TRUE,"BAD")} -> Excellent
... A501: 172.27 | B501: 54.13 | C501: =B501/A501 -> 0.31421606 | D501: {=_xlfn.IFS(AND(C501>20%, A501>2000),"Excellent", AND(C501<20%, C501>10%),"Good",TRUE,"BAD")} -> BAD

Sheet Q5
B2: Origin_Country | C2: Supplier | E2: Region code | F2: Region Name
B3: China | C3: =IFERROR(INDEX(Product_Master!$A$2:$F$11,MATCH(B3,Product_Master!$E$2:$E$11,0),4),"Not Found") -> AudioTech Ltd. | E3: NA | F3: =IFERROR(VLOOKUP(E3,Region!$A$2:$D$7,2,0),"Not Found") -> North America
B4: India | C4: =INDEX(Product_Master!$A$2:$F$11,MATCH(B4,Product_Master!$E$2:$E$11,0),4) -> Artisans Co. | E4: EU | F4: =VLOOKUP(E4,Region!$A$2:$D$7,2,0) -> Europe
B5: Italy | C5: =INDEX(Product_Master!$A$2:$F$11,MATCH(B5,Product_Master!$E$2:$E$11,0),4) -> CraftLine | E5: AS | F5: =VLOOKUP(E5,Region!$A$2:$D$7,2,0) -> Asia
B6: Vietnam | C6: =INDEX(Product_Master!$A$2:$F$11,MATCH(B6,Product_Master!$E$2:$E$11,0),4) -> BrightHome | E6: AF | F6: =VLOOKUP(E6,Region!$A$2:$D$7,2,0) -> Africa
B7: Turkey | C7: =INDEX(Product_Master!$A$2:$F$11,MATCH(B7,Product_Master!$E$2:$E$11,0),4) -> SoftWeave | E7: SA | F7: =VLOOKUP(E7,Region!$A$2:$D$7,2,0) -> South America
B8: China | C8: =INDEX(Product_Master!$A$2:$F$11,MATCH(B8,Product_Master!$E$2:$E$11,0),4) -> AudioTech Ltd. | E8: OC | F8: =VLOOKUP(E8,Region!$A$2:$D$7,2,0) -> Oceania
B9: India | C9: =INDEX(Product_Master!$A$2:$F$11,MATCH(B9,Product_Master!$E$2:$E$11,0),4) -> Artisans Co.
B10: Vietnam | C10: =INDEX(Product_Master!$A$2:$F$11,MATCH(B10,Product_Master!$E$2:$E$11,0),4) -> BrightHome
B11: India | C11: =INDEX(Product_Master!$A$2:$F$11,MATCH(B11,Product_Master!$E$2:$E$11,0),4) -> Artisans Co.
B12: Bangladesh | C12: =INDEX(Product_Master!$A$2:$F$11,MATCH(B12,Product_Master!$E$2:$E$11,0),4) -> BlueWear

Sheet Q6
A1: Region_Code | B1: Category | C1: Total_Sales | D1: Total Profit | E1: Avg Sales | F1: Avg Profits
A2: NA | B2: Accessories | C2: =SUMIFS(Global_trade!I2:I501,Global_trade!F2:F501,B2,Global_trade!N2:N501,A2) -> 24079.71 | D2: =SUMIFS(Global_trade!K2:K501,Global_trade!F2:F501,'Q6'!B2,Global_trade!N2:N501,'Q6'!A2) -> 6581.57 | E2: =AVERAGEIFS(Global_trade!I2:I501,Global_trade!F2:F501,'Q6'!B2,Global_trade!N2:N501,'Q6'!A2) -> 1203.9855 | F2: =AVERAGEIFS(Global_trade!K2:K501,Global_trade!F2:F501,'Q6'!B2,Global_trade!N2:N501,'Q6'!A2) -> 329.0785
A3: EU | B3: Accessories | C3: =SUMIFS(Global_trade!I3:I502,Global_trade!F3:F502,B3,Global_trade!N3:N502,A3) -> 30642.08 | D3: =SUMIFS(Global_trade!K3:K502,Global_trade!F3:F502,'Q6'!B3,Global_trade!N3:N502,'Q6'!A3) -> 8020.69 | E3: =AVERAGEIFS(Global_trade!I3:I502,Global_trade!F3:F502,'Q6'!B3,Global_trade!N3:N502,'Q6'!A3) -> 1056.6234 | F3: =AVERAGEIFS(Global_trade!K3:K502,Global_trade!F3:F502,'Q6'!B3,Global_trade!N3:N502,'Q6'!A3) -> 276.57552
A4: EU | B4: Accessories | C4: =SUMIFS(Global_trade!I4:I503,Global_trade!F4:F503,B4,Global_trade!N4:N503,A4) -> 29585.09 | D4: =SUMIFS(Global_trade!K4:K503,Global_trade!F4:F503,'Q6'!B4,Global_trade!N4:N503,'Q6'!A4) -> 7617.29 | E4: =AVERAGEIFS(Global_trade!I4:I503,Global_trade!F4:F503,'Q6'!B4,Global_trade!N4:N503,'Q6'!A4) -> 1056.6104 | F4: =AVERAGEIFS(Global_trade!K4:K503,Global_trade!F4:F503,'Q6'!B4,Global_trade!N4:N503,'Q6'!A4) -> 272.04607
A5: SA | B5: Electronics | C5: =SUMIFS(Global_trade!I5:I504,Global_trade!F5:F504,B5,Global_trade!N5:N504,A5) -> 16927.67 | D5: =SUMIFS(Global_trade!K5:K504,Global_trade!F5:F504,'Q6'!B5,Global_trade!N5:N504,'Q6'!A5) -> 4721.5 | E5: =AVERAGEIFS(Global_trade!I5:I504,Global_trade!F5:F504,'Q6'!B5,Global_trade!N5:N504,'Q6'!A5) -> 890.93 | F5: =AVERAGEIFS(Global_trade!K5:K504,Global_trade!F5:F504,'Q6'!B5,Global_trade!N5:N504,'Q6'!A5) -> 248.5
A6: NA | B6: Apparel | C6: =SUMIFS(Global_trade!I6:I505,Global_trade!F6:F505,B6,Global_trade!N6:N505,A6) -> 9625.97 | D6: =SUMIFS(Global_trade!K6:K505,Global_trade!F6:F505,'Q6'!B6,Global_trade!N6:N505,'Q6'!A6) -> 3119.22 | E6: =AVERAGEIFS(Global_trade!I6:I505,Global_trade!F6:F505,'Q6'!B6,Global_trade!N6:N505,'Q6'!A6) -> 1925.194 | F6: =AVERAGEIFS(Global_trade!K6:K505,Global_trade!F6:F505,'Q6'!B6,Global_trade!N6:N505,'Q6'!A6) -> 623.844
A7: NA | B7: Electronics | C7: =SUMIFS(Global_trade!I7:I506,Global_trade!F7:F506,B7,Global_trade!N7:N506,A7) -> 22495.01 | D7: =SUMIFS(Global_trade!K7:K506,Global_trade!F7:F506,'Q6'!B7,Global_trade!N7:N506,'Q6'!A7) -> 5558.34 | E7: =AVERAGEIFS(Global_trade!I7:I506,Global_trade!F7:F506,'Q6'!B7,Global_trade!N7:N506,'Q6'!A7) -> 775.69 | F7: =AVERAGEIFS(Global_trade!K7:K506,Global_trade!F7:F506,'Q6'!B7,Global_trade!N7:N506,'Q6'!A7) -> 191.6669
A8: EU | B8: Home Decor | C8: =SUMIFS(Global_trade!I8:I507,Global_trade!F8:F507,B8,Global_trade!N8:N507,A8) -> 33685.94 | D8: =SUMIFS(Global_trade!K8:K507,Global_trade!F8:F507,'Q6'!B8,Global_trade!N8:N507,'Q6'!A8) -> 9028.2 | E8: =AVERAGEIFS(Global_trade!I8:I507,Global_trade!F8:F507,'Q6'!B8,Global_trade!N8:N507,'Q6'!A8) -> 765.58955 | F8: =AVERAGEIFS(Global_trade!K8:K507,Global_trade!F8:F507,'Q6'!B8,Global_trade!N8:N507,'Q6'!A8) -> 205.18636
A9: AS | B9: Textiles | C9: =SUMIFS(Global_trade!I9:I508,Global_trade!F9:F508,B9,Global_trade!N9:N508,A9) -> 21644.31 | D9: =SUMIFS(Global_trade!K9:K508,Global_trade!F9:F508,'Q6'!B9,Global_trade!N9:N508,'Q6'!A9) -> 5965.63 | E9: =AVERAGEIFS(Global_trade!I9:I508,Global_trade!F9:F508,'Q6'!B9,Global_trade!N9:N508,'Q6'!A9) -> 832.47346 | F9: =AVERAGEIFS(Global_trade!K9:K508,Global_trade!F9:F508,'Q6'!B9,Global_trade!N9:N508,'Q6'!A9) -> 229.44731
A10: NA | B10: Home Decor | C10: =SUMIFS(Global_trade!I10:I509,Global_trade!F10:F509,B10,Global_trade!N10:N509,A10) -> 26924.32 | D10: =SUMIFS(Global_trade!K10:K509,Global_trade!F10:F509,'Q6'!B10,Global_trade!N10:N509,'Q6'!A10) -> 7966.09 | E10: =AVERAGEIFS(Global_trade!I10:I509,Global_trade!F10:F509,'Q6'!B10,Global_trade!N10:N509,'Q6'!A10) -> 997.19704 | F10: =AVERAGEIFS(Global_trade!K10:K509,Global_trade!F10:F509,'Q6'!B10,Global_trade!N10:N509,'Q6'!A10) -> 295.04037
A11: EU | B11: Electronics | C11: =SUMIFS(Global_trade!I11:I510,Global_trade!F11:F510,B11,Global_trade!N11:N510,A11) -> 25086.15 | D11: =SUMIFS(Global_trade!K11:K510,Global_trade!F11:F510,'Q6'!B11,Global_trade!N11:N510,'Q6'!A11) -> 7458.03 | E11: =AVERAGEIFS(Global_trade!I11:I510,Global_trade!F11:F510,'Q6'!B11,Global_trade!N11:N510,'Q6'!A11) -> 696.8375 | F11: =AVERAGEIFS(Global_trade!K11:K510,Global_trade!F11:F510,'Q6'!B11,Global_trade!N11:N510,'Q6'!A11) -> 207.1675
A12: AS | B12: Accessories | C12: =SUMIFS(Global_trade!I12:I511,Global_trade!F12:F511,B12,Global_trade!N12:N511,A12) -> 33225.64 | D12: =SUMIFS(Global_trade!K12:K511,Global_trade!F12:F511,'Q6'!B12,Global_trade!N12:N511,'Q6'!A12) -> 9628.14 | E12: =AVERAGEIFS(Global_trade!I12:I511,Global_trade!F12:F511,'Q6'!B12,Global_trade!N12:N511,'Q6'!A12) -> 977.22471 | F12: =AVERAGEIFS(Global_trade!K12:K511,Global_trade!F12:F511,'Q6'!B12,Global_trade!N12:N511,'Q6'!A12) -> 283.18059
A13: NA | B13: Apparel | C13: =SUMIFS(Global_trade!I13:I512,Global_trade!F13:F512,B13,Global_trade!N13:N512,A13) -> 8449.23 | D13: =SUMIFS(Global_trade!K13:K512,Global_trade!F13:F512,'Q6'!B13,Global_trade!N13:N512,'Q6'!A13) -> 2688.42 | E13: =AVERAGEIFS(Global_trade!I13:I512,Global_trade!F13:F512,'Q6'!B13,Global_trade!N13:N512,'Q6'!A13) -> 2112.3075 | F13: =AVERAGEIFS(Global_trade!K13:K512,Global_trade!F13:F512,'Q6'!B13,Global_trade!N13:N512,'Q6'!A13) -> 672.105
... A501: EU | B501: Home Decor | C501: =SUMIFS(Global_trade!I501:I1000,Global_trade!F501:F1000,B501,Global_trade!N501:N1000,A501) -> 172.27 | D501: =SUMIFS(Global_trade!K501:K1000,Global_trade!F501:F1000,'Q6'!B501,Global_trade!N501:N1000,'Q6'!A501) -> 54.13 | E501: =AVERAGEIFS(Global_trade!I501:I1000,Global_trade!F501:F1000,'Q6'!B501,Global_trade!N501:N1000,'Q6'!A501) -> 172.27 | F501: =AVERAGEIFS(Global_trade!K501:K1000,Global_trade!F501:F1000,'Q6'!B501,Global_trade!N501:N1000,'Q6'!A501) -> 54.13

Sheet Q7-Data
A1: Order_ID | B1: Order_Date | C1: Customer_Name | D1: Country | E1: Product | F1: Category | G1: Quantity | H1: Unit_Price | I1: Total_Sales | J1: Shipping_Cost | K1: Profit | L1: Ship_Mode | M1: Order_Priority | N1: Region_Code | O1: Unit_Cost | P1: Supplier | Q1: Origin_Country | R1: Month
A2: ORD_2025_0001 | B2: 45677 | C2: Smith, Emily | D2: USA | E2: Travel Backpack | F2: Accessories | G2: 20 | H2: 55.22 | I2: 1104.4 | J2: 49.36 | K2: 355.04 | L2: Land | M2: Low | N2: NA | O2: 35 | P2: CarryPro | Q2: Vietnam | R2: 2025-01
A3: ORD_2025_0002 | B3: 45702 | C3: Brown, Laura | D3: UK | E3: Leather Wallet | F3: Accessories | G3: 33 | H3: 32.03 | I3: 1056.99 | J3: 59.59 | K3: 403.4 | L3: Sea | M3: Medium | N3: EU | O3: 18 | P3: CraftLine | Q3: Italy | R3: 2025-02
A4: ORD_2025_0003 | B4: 45411 | C4: Davis, John | D4: Italy | E4: Leather Wallet | F4: Accessories | G4: 34 | H4: 28.48 | I4: 968.32 | J4: 73.95 | K4: 282.37 | L4: Land | M4: High | N4: EU | O4: 18 | P4: CraftLine | Q4: Italy | R4: 2024-04
A5: ORD_2025_0004 | B5: 45566 | C5: Miller, Daniel | D5: Brazil | E5: Bluetooth Speaker | F5: Electronics | G5: 6 | H5: 56.36 | I5: 338.16 | J5: 11.39 | K5: 134.77 | L5: Air | M5: Medium | N5: SA | O5: 32 | P5: AudioTech Ltd. | Q5: China | R5: 2024-10
A6: ORD_2025_0005 | B6: 45703 | C6: Johnson, Emma | D6: Canada | E6: Denim Jacket | F6: Apparel | G6: 17 | H6: 69.22 | I6: 1176.74 | J6: 65.94 | K6: 430.8 | L6: Sea | M6: Low | N6: NA | O6: 40 | P6: BlueWear | Q6: Bangladesh | R6: 2025-02
A7: ORD_2025_0006 | B7: 45714 | C7: Johnson, Michael | D7: Mexico | E7: Wireless Mouse | F7: Electronics | G7: 13 | H7: 27.94 | I7: 363.22 | J7: 15.36 | K7: 87.86 | L7: Sea | M7: Low | N7: NA | O7: 20 | P7: ClickTech | Q7: China | R7: 2025-02
A8: ORD_2025_0007 | B8: 45456 | C8: Hernandez, Emma | D8: UK | E8: Glass Bowl Set | F8: Home Decor | G8: 3 | H8: 31.52 | I8: 94.56 | J8: 6.98 | K8: 20.08 | L8: Land | M8: High | N8: EU | O8: 22.5 | P8: ClearCraft | Q8: India | R8: 2024-06
A9: ORD_2025_0008 | B9: 45778 | C9: Miller, John | D9: China | E9: Cotton Bedsheet | F9: Textiles | G9: 14 | H9: 30.71 | I9: 429.94 | J9: 13.03 | K9: 66.91 | L9: Sea | M9: Low | N9: AS | O9: 25 | P9: SoftWeave | Q9: Turkey | R9: 2025-05
A10: ORD_2025_0009 | B10: 45548 | C10: Davis, John | D10: USA | E10: Ceramic Vase | F10: Home Decor | G10: 47 | H10: 24.47 | I10: 1150.09 | J10: 61.3 | K10: 360.29 | L10: Sea | M10: Low | N10: NA | O10: 15.5 | P10: Artisans Co. | Q10: India | R10: 2024-09
A11: ORD_2025_0010 | B11: 45531 | C11: Martinez, Laura | D11: Italy | E11: LED Lamp | F11: Electronics | G11: 27 | H11: 18.98 | I11: 512.46 | J11: 28.89 | K11: 139.32 | L11: Sea | M11: High | N11: EU | O11: 12.75 | P11: BrightHome | Q11: Vietnam | R11: 2024-08

Sheet Sheet7

Sheet Q8
A3: Row Labels | B3: Sum of Total_Sales | C3: Sum of Profit
A4: 2024 | B4: 345682.78 | C4: 95686.42
A5: Jan | B5: 23642.31 | C5: 6054.28
A6: Feb | B6: 29912 | C6: 9234.03
A7: Mar | B7: 27450.58 | C7: 7448.97
A8: Apr | B8: 14076.35 | C8: 4322.61
A9: May | B9: 25044.65 | C9: 6249.32
A10: Jun | B10: 38692.6 | C10: 11775.91
A11: Jul | B11: 30288.91 | C11: 8441.19
A12: Aug | B12: 28579.07 | C12: 7976.39
A13: Sep | B13: 31738.73 | C13: 8387.18
A14: Oct | B14: 25371.88 | C14: 7552.51
A15: Nov | B15: 31766.41 | C15: 7763.13
... A23: Grand Total | B23: 474704.62 | C23: 133528.36

Sheet Sheet8

Sheet Sheet1
A1: i | B1: Order_Date | C1: Customer_Name | D1: Country | E1: Product | F1: Category | G1: Quantity | H1: Unit_Price | I1: Total_Sales | J1: Shipping_Cost | K1: Profit | L1: Ship_Mode | M1: Order_Priority | N1: Region_Code | O1: Unit_cost | P1: COGS | Q1: Profit Margin
A2: ORD_2025_0001 | B2: Jan-2025 | C2: Smith, Emily | D2: Usa | E2: Travel Backpack | F2: Accessories | G2: 20 | H2: 55.22 | I2: 1104.4 | J2: 49.36 | K2: 355.04 | L2: Land | M2: Low | N2: NA | O2: =_xlfn.XLOOKUP(E2,Product_Master!$B$2:$B$11,Product_Master!$F$2:$F$11) -> 35 | P2: =G2*O2 -> 700 | Q2: =K2/I2 -> 0.32147773
A3: ORD_2025_0002 | B3: Feb-2025 | C3: Brown, Laura | D3: Uk | E3: Leather Wallet | F3: Accessories | G3: 33 | H3: 32.03 | I3: 1056.99 | J3: 59.59 | K3: 403.4 | L3: Sea | M3: Medium | N3: EU | O3: =_xlfn.XLOOKUP(E3,Product_Master!$B$2:$B$11,Product_Master!$F$2:$F$11) -> 18 | P3: =G3*O3 -> 594 | Q3: =K3/I3 -> 0.38164978
A4: ORD_2025_0003 | B4: Apr-2024 | C4: Davis, John | D4: Italy | E4: Leather Wallet | F4: Accessories | G4: 34 | H4: 28.48 | I4: 968.32 | J4: 73.95 | K4: 282.37 | L4: Land | M4: High | N4: EU | O4: =_xlfn.XLOOKUP(E4,Product_Master!$B$2:$B$11,Product_Master!$F$2:$F$11) -> 18 | P4: =G4*O4 -> 612 | Q4: =K4/I4 -> 0.29160815
A5: ORD_2025_0004 | B5: Oct-2024 | C5: Miller, Daniel | D5: Brazil | E5: Bluetooth Speaker | F5: Electronics | G5: 6 | H5: 56.36 | I5: 338.16 | J5: 11.39 | K5: 134.77 | L5: Air | M5: Medium | N5: SA | O5: =_xlfn.XLOOKUP(E5,Product_Master!$B$2:$B$11,Product_Master!$F$2:$F$11) -> 32 | P5: =G5*O5 -> 192 | Q5: =K5/I5 -> 0.39853915
A6: ORD_2025_0005 | B6: Feb-2025 | C6: Johnson, Emma | D6: Canada | E6: Denim Jacket | F6: Apparel | G6: 17 | H6: 69.22 | I6: 1176.74 | J6: 65.94 | K6: 430.8 | L6: Sea | M6: Low | N6: NA | O6: =_xlfn.XLOOKUP(E6,Product_Master!$B$2:$B$11,Product_Master!$F$2:$F$11) -> 40 | P6: =G6*O6 -> 680 | Q6: =K6/I6 -> 0.36609616
A7: ORD_2025_0006 | B7: Feb-2025 | C7: Johnson, Michael | D7: Mexico | E7: Wireless Mouse | F7: Electronics | G7: 13 | H7: 27.94 | I7: 363.22 | J7: 15.36 | K7: 87.86 | L7: Sea | M7: Low | N7: NA | O7: =_xlfn.XLOOKUP(E7,Product_Master!$B$2:$B$11,Product_Master!$F$2:$F$11) -> 20 | P7: =G7*O7 -> 260 | Q7: =K7/I7 -> 0.24189197
A8: ORD_2025_0007 | B8: Jun-2024 | C8: Hernandez, Emma | D8: Uk | E8: Glass Bowl Set | F8: Home Decor | G8: 3 | H8: 31.52 | I8: 94.56 | J8: 6.98 | K8: 20.08 | L8: Land | M8: High | N8: EU | O8: =_xlfn.XLOOKUP(E8,Product_Master!$B$2:$B$11,Product_Master!$F$2:$F$11) -> 22.5 | P8: =G8*O8 -> 67.5 | Q8: =K8/I8 -> 0.21235195
A9: ORD_2025_0008 | B9: May-2025 | C9: Miller, John | D9: China | E9: Cotton Bedsheet | F9: Textiles | G9: 14 | H9: 30.71 | I9: 429.94 | J9: 13.03 | K9: 66.91 | L9: Sea | M9: Low | N9: AS | O9: =_xlfn.XLOOKUP(E9,Product_Master!$B$2:$B$11,Product_Master!$F$2:$F$11) -> 25 | P9: =G9*O9 -> 350 | Q9: =K9/I9 -> 0.15562637
A10: ORD_2025_0009 | B10: Sep-2024 | C10: Davis, John | D10: Usa | E10: Ceramic Vase | F10: Home Decor | G10: 47 | H10: 24.47 | I10: 1150.09 | J10: 61.3 | K10: 360.29 | L10: Sea | M10: Low | N10: NA | O10: =_xlfn.XLOOKUP(E10,Product_Master!$B$2:$B$11,Product_Master!$F$2:$F$11) -> 15.5 | P10: =G10*O10 -> 728.5 | Q10: =K10/I10 -> 0.31327114
A11: ORD_2025_0010 | B11: Aug-2024 | C11: Martinez, Laura | D11: Italy | E11: LED Lamp | F11: Electronics | G11: 27 | H11: 18.98 | I11: 512.46 | J11: 28.89 | K11: 139.32 | L11: Sea | M11: High | N11: EU | O11: =_xlfn.XLOOKUP(E11,Product_Master!$B$2:$B$11,Product_Master!$F$2:$F$11) -> 12.75 | P11: =G11*O11 -> 344.25 | Q11: =K11/I11 -> 0.27186512
A12: ORD_2025_0011 | B12: Apr-2025 | C12: Martinez, James | D12: China | E12: Travel Backpack | F12: Accessories | G12: 32 | H12: 57.84 | I12: 1850.88 | J12: 55.15 | K12: 675.73 | L12: Land | M12: Low | N12: AS | O12: =_xlfn.XLOOKUP(E12,Product_Master!$B$2:$B$11,Product_Master!$F$2:$F$11) -> 35 | P12: =G12*O12 -> 1120 | Q12: =K12/I12 -> 0.3650858
A13: ORD_2025_0012 | B13: Dec-2024 | C13: Davis, James | D13: Canada | E13: Denim Jacket | F13: Apparel | G13: 49 | H13: 58.77 | I13: 2879.73 | J13: 140.29 | K13: 779.44 | L13: Air | M13: High | N13: NA | O13: =_xlfn.XLOOKUP(E13,Product_Master!$B$2:$B$11,Product_Master!$F$2:$F$11) -> 40 | P13: =G13*O13 -> 1960 | Q13: =K13/I13 -> 0.27066426
... A501: ORD_2025_0500 | B501: 2024-07-14 | C501: Hernandez, Michael | D501: Uk | E501: Ceramic Vase | F501: Home Decor | G501: 7 | H501: 24.61 | I501: 172.27 | J501: 9.64 | K501: 54.13 | L501: Air | M501: High | N501: EU | O501: =_xlfn.XLOOKUP(E501,Product_Master!$B$2:$B$11,Product_Master!$F$2:$F$11) -> 15.5 | P501: =G501*O501 -> 108.5 | Q501: =K501/I501 -> 0.31421606

Sheet Sheet2
A1: i | B1: Order_Date | C1: Customer_Name | D1: Country | E1: Product | F1: Category | G1: Quantity | H1: Unit_Price | I1: Total_Sales | J1: Shipping_Cost | K1: Profit | L1: Ship_Mode | M1: Order_Priority | N1: Region_Code | O1: Unit_cost | P1: COGS | Q1: Profit Margin
A2: ORD_2025_0001 | B2: Jan-2025 | C2: Smith, Emily | D2: Usa | E2: Travel Backpack | F2: Accessories | G2: 20 | H2: 55.22 | I2: 1104.4 | J2: 49.36 | K2: 355.04 | L2: Land | M2: Low | N2: NA | O2: =_xlfn.XLOOKUP(E2,Product_Master!$B$2:$B$11,Product_Master!$F$2:$F$11) -> 35 | P2: =G2*O2 -> 700 | Q2: =K2/I2 -> 0.32147773
A3: ORD_2025_0002 | B3: Feb-2025 | C3: Brown, Laura | D3: Uk | E3: Leather Wallet | F3: Accessories | G3: 33 | H3: 32.03 | I3: 1056.99 | J3: 59.59 | K3: 403.4 | L3: Sea | M3: Medium | N3: EU | O3: =_xlfn.XLOOKUP(E3,Product_Master!$B$2:$B$11,Product_Master!$F$2:$F$11) -> 18 | P3: =G3*O3 -> 594 | Q3: =K3/I3 -> 0.38164978
A4: ORD_2025_0003 | B4: Apr-2024 | C4: Davis, John | D4: Italy | E4: Leather Wallet | F4: Accessories | G4: 34 | H4: 28.48 | I4: 968.32 | J4: 73.95 | K4: 282.37 | L4: Land | M4: High | N4: EU | O4: =_xlfn.XLOOKUP(E4,Product_Master!$B$2:$B$11,Product_Master!$F$2:$F$11) -> 18 | P4: =G4*O4 -> 612 | Q4: =K4/I4 -> 0.29160815
A5: ORD_2025_0004 | B5: Oct-2024 | C5: Miller, Daniel | D5: Brazil | E5: Bluetooth Speaker | F5: Electronics | G5: 6 | H5: 56.36 | I5: 338.16 | J5: 11.39 | K5: 134.77 | L5: Air | M5: Medium | N5: SA | O5: =_xlfn.XLOOKUP(E5,Product_Master!$B$2:$B$11,Product_Master!$F$2:$F$11) -> 32 | P5: =G5*O5 -> 192 | Q5: =K5/I5 -> 0.39853915
A6: ORD_2025_0005 | B6: Feb-2025 | C6: Johnson, Emma | D6: Canada | E6: Denim Jacket | F6: Apparel | G6: 17 | H6: 69.22 | I6: 1176.74 | J6: 65.94 | K6: 430.8 | L6: Sea | M6: Low | N6: NA | O6: =_xlfn.XLOOKUP(E6,Product_Master!$B$2:$B$11,Product_Master!$F$2:$F$11) -> 40 | P6: =G6*O6 -> 680 | Q6: =K6/I6 -> 0.36609616
A7: ORD_2025_0006 | B7: Feb-2025 | C7: Johnson, Michael | D7: Mexico | E7: Wireless Mouse | F7: Electronics | G7: 13 | H7: 27.94 | I7: 363.22 | J7: 15.36 | K7: 87.86 | L7: Sea | M7: Low | N7: NA | O7: =_xlfn.XLOOKUP(E7,Product_Master!$B$2:$B$11,Product_Master!$F$2:$F$11) -> 20 | P7: =G7*O7 -> 260 | Q7: =K7/I7 -> 0.24189197
A8: ORD_2025_0007 | B8: Jun-2024 | C8: Hernandez, Emma | D8: Uk | E8: Glass Bowl Set | F8: Home Decor | G8: 3 | H8: 31.52 | I8: 94.56 | J8: 6.98 | K8: 20.08 | L8: Land | M8: High | N8: EU | O8: =_xlfn.XLOOKUP(E8,Product_Master!$B$2:$B$11,Product_Master!$F$2:$F$11) -> 22.5 | P8: =G8*O8 -> 67.5 | Q8: =K8/I8 -> 0.21235195
A9: ORD_2025_0008 | B9: May-2025 | C9: Miller, John | D9: China | E9: Cotton Bedsheet | F9: Textiles | G9: 14 | H9: 30.71 | I9: 429.94 | J9: 13.03 | K9: 66.91 | L9: Sea | M9: Low | N9: AS | O9: =_xlfn.XLOOKUP(E9,Product_Master!$B$2:$B$11,Product_Master!$F$2:$F$11) -> 25 | P9: =G9*O9 -> 350 | Q9: =K9/I9 -> 0.15562637
A10: ORD_2025_0009 | B10: Sep-2024 | C10: Davis, John | D10: Usa | E10: Ceramic Vase | F10: Home Decor | G10: 47 | H10: 24.47 | I10: 1150.09 | J10: 61.3 | K10: 360.29 | L10: Sea | M10: Low | N10: NA | O10: =_xlfn.XLOOKUP(E10,Product_Master!$B$2:$B$11,Product_Master!$F$2:$F$11) -> 15.5 | P10: =G10*O10 -> 728.5 | Q10: =K10/I10 -> 0.31327114
A11: ORD_2025_0010 | B11: Aug-2024 | C11: Martinez, Laura | D11: Italy | E11: LED Lamp | F11: Electronics | G11: 27 | H11: 18.98 | I11: 512.46 | J11: 28.89 | K11: 139.32 | L11: Sea | M11: High | N11: EU | O11: =_xlfn.XLOOKUP(E11,Product_Master!$B$2:$B$11,Product_Master!$F$2:$F$11) -> 12.75 | P11: =G11*O11 -> 344.25 | Q11: =K11/I11 -> 0.27186512
A12: ORD_2025_0011 | B12: Apr-2025 | C12: Martinez, James | D12: China | E12: Travel Backpack | F12: Accessories | G12: 32 | H12: 57.84 | I12: 1850.88 | J12: 55.15 | K12: 675.73 | L12: Land | M12: Low | N12: AS | O12: =_xlfn.XLOOKUP(E12,Product_Master!$B$2:$B$11,Product_Master!$F$2:$F$11) -> 35 | P12: =G12*O12 -> 1120 | Q12: =K12/I12 -> 0.3650858
A13: ORD_2025_0012 | B13: Dec-2024 | C13: Davis, James | D13: Canada | E13: Denim Jacket | F13: Apparel | G13: 49 | H13: 58.77 | I13: 2879.73 | J13: 140.29 | K13: 779.44 | L13: Air | M13: High | N13: NA | O13: =_xlfn.XLOOKUP(E13,Product_Master!$B$2:$B$11,Product_Master!$F$2:$F$11) -> 40 | P13: =G13*O13 -> 1960 | Q13: =K13/I13 -> 0.27066426
... A501: ORD_2025_0500 | B501: 2024-07-14 | C501: Hernandez, Michael | D501: Uk | E501: Ceramic Vase | F501: Home Decor | G501: 7 | H501: 24.61 | I501: 172.27 | J501: 9.64 | K501: 54.13 | L501: Air | M501: High | N501: EU | O501: =_xlfn.XLOOKUP(E501,Product_Master!$B$2:$B$11,Product_Master!$F$2:$F$11) -> 15.5 | P501: =G501*O501 -> 108.5 | Q501: =K501/I501 -> 0.31421606

Sheet Q10 Data
A1: i | B1: Order_Date | C1: Customer_Name | D1: Country | E1: Product | F1: Category | G1: Quantity | H1: Unit_Price | I1: Total_Sales | J1: Shipping_Cost | K1: Profit | L1: Ship_Mode | M1: Order_Priority | N1: Region_Code | O1: Profit Margin | P1: Clean Date | Q1: Supplier | R1: Origin_Country | S1: Unit_Cost
A2: ORD_2025_0001 | B2: Jan-2025 | C2: Smith, Emily | D2: Usa | E2: Travel Backpack | F2: Accessories | G2: 20 | H2: 55.22 | I2: 1104.4 | J2: 49.36 | K2: 355.04 | L2: Land | M2: Low | N2: NA | O2: =Table14[[#This Row],[Profit]]/Table14[[#This Row],[Total_Sales]] -> 0.32147773 | P2: =DATE(YEAR(Table14[[#This Row],[Order_Date]]), MONTH(Table14[[#This Row],[Order_Date]]), 1) -> 45658 | Q2: =_xlfn.XLOOKUP(Table14[[#This Row],[Product]],Product_Master!$B$2:$B$11,Product_Master!$D$2:$D$11) -> CarryPro | R2: =_xlfn.XLOOKUP(Table14[[#This Row],[Product]],Product_Master!$B$2:$B$11,Product_Master!$E$2:$E$11) -> Vietnam | S2: =_xlfn.XLOOKUP(Table14[[#This Row],[Product]],Product_Master!$B$2:$B$11,Product_Master!$F$2:$F$11) -> 35
A3: ORD_2025_0002 | B3: Feb-2025 | C3: Brown, Laura | D3: Uk | E3: Leather Wallet | F3: Accessories | G3: 33 | H3: 32.03 | I3: 1056.99 | J3: 59.59 | K3: 403.4 | L3: Sea | M3: Medium | N3: EU | O3: =Table14[[#This Row],[Profit]]/Table14[[#This Row],[Total_Sales]] -> 0.38164978 | P3: =DATE(YEAR(Table14[[#This Row],[Order_Date]]), MONTH(Table14[[#This Row],[Order_Date]]), 1) -> 45689 | Q3: =_xlfn.XLOOKUP(Table14[[#This Row],[Product]],Product_Master!$B$2:$B$11,Product_Master!$D$2:$D$11) -> CraftLine | R3: =_xlfn.XLOOKUP(Table14[[#This Row],[Product]],Product_Master!$B$2:$B$11,Product_Master!$E$2:$E$11) -> Italy | S3: =_xlfn.XLOOKUP(Table14[[#This Row],[Product]],Product_Master!$B$2:$B$11,Product_Master!$F$2:$F$11) -> 18
A4: ORD_2025_0003 | B4: Apr-2024 | C4: Davis, John | D4: Italy | E4: Leather Wallet | F4: Accessories | G4: 34 | H4: 28.48 | I4: 968.32 | J4: 73.95 | K4: 282.37 | L4: Land | M4: High | N4: EU | O4: =Table14[[#This Row],[Profit]]/Table14[[#This Row],[Total_Sales]] -> 0.29160815 | P4: =DATE(YEAR(Table14[[#This Row],[Order_Date]]), MONTH(Table14[[#This Row],[Order_Date]]), 1) -> 45383 | Q4: =_xlfn.XLOOKUP(Table14[[#This Row],[Product]],Product_Master!$B$2:$B$11,Product_Master!$D$2:$D$11) -> CraftLine | R4: =_xlfn.XLOOKUP(Table14[[#This Row],[Product]],Product_Master!$B$2:$B$11,Product_Master!$E$2:$E$11) -> Italy | S4: =_xlfn.XLOOKUP(Table14[[#This Row],[Product]],Product_Master!$B$2:$B$11,Product_Master!$F$2:$F$11) -> 18
A5: ORD_2025_0004 | B5: Oct-2024 | C5: Miller, Daniel | D5: Brazil | E5: Bluetooth Speaker | F5: Electronics | G5: 6 | H5: 56.36 | I5: 338.16 | J5: 11.39 | K5: 134.77 | L5: Air | M5: Medium | N5: SA | O5: =Table14[[#This Row],[Profit]]/Table14[[#This Row],[Total_Sales]] -> 0.39853915 | P5: =DATE(YEAR(Table14[[#This Row],[Order_Date]]), MONTH(Table14[[#This Row],[Order_Date]]), 1) -> 45566 | Q5: =_xlfn.XLOOKUP(Table14[[#This Row],[Product]],Product_Master!$B$2:$B$11,Product_Master!$D$2:$D$11) -> AudioTech Ltd. | R5: =_xlfn.XLOOKUP(Table14[[#This Row],[Product]],Product_Master!$B$2:$B$11,Product_Master!$E$2:$E$11) -> China | S5: =_xlfn.XLOOKUP(Table14[[#This Row],[Product]],Product_Master!$B$2:$B$11,Product_Master!$F$2:$F$11) -> 32
A6: ORD_2025_0005 | B6: Feb-2025 | C6: Johnson, Emma | D6: Canada | E6: Denim Jacket | F6: Apparel | G6: 17 | H6: 69.22 | I6: 1176.74 | J6: 65.94 | K6: 430.8 | L6: Sea | M6: Low | N6: NA | O6: =Table14[[#This Row],[Profit]]/Table14[[#This Row],[Total_Sales]] -> 0.36609616 | P6: =DATE(YEAR(Table14[[#This Row],[Order_Date]]), MONTH(Table14[[#This Row],[Order_Date]]), 1) -> 45689 | Q6: =_xlfn.XLOOKUP(Table14[[#This Row],[Product]],Product_Master!$B$2:$B$11,Product_Master!$D$2:$D$11) -> BlueWear | R6: =_xlfn.XLOOKUP(Table14[[#This Row],[Product]],Product_Master!$B$2:$B$11,Product_Master!$E$2:$E$11) -> Bangladesh | S6: =_xlfn.XLOOKUP(Table14[[#This Row],[Product]],Product_Master!$B$2:$B$11,Product_Master!$F$2:$F$11) -> 40
A7: ORD_2025_0006 | B7: Feb-2025 | C7: Johnson, Michael | D7: Mexico | E7: Wireless Mouse | F7: Electronics | G7: 13 | H7: 27.94 | I7: 363.22 | J7: 15.36 | K7: 87.86 | L7: Sea | M7: Low | N7: NA | O7: =Table14[[#This Row],[Profit]]/Table14[[#This Row],[Total_Sales]] -> 0.24189197 | P7: =DATE(YEAR(Table14[[#This Row],[Order_Date]]), MONTH(Table14[[#This Row],[Order_Date]]), 1) -> 45689 | Q7: =_xlfn.XLOOKUP(Table14[[#This Row],[Product]],Product_Master!$B$2:$B$11,Product_Master!$D$2:$D$11) -> ClickTech | R7: =_xlfn.XLOOKUP(Table14[[#This Row],[Product]],Product_Master!$B$2:$B$11,Product_Master!$E$2:$E$11) -> China | S7: =_xlfn.XLOOKUP(Table14[[#This Row],[Product]],Product_Master!$B$2:$B$11,Product_Master!$F$2:$F$11) -> 20
A8: ORD_2025_0007 | B8: Jun-2024 | C8: Hernandez, Emma | D8: Uk | E8: Glass Bowl Set | F8: Home Decor | G8: 3 | H8: 31.52 | I8: 94.56 | J8: 6.98 | K8: 20.08 | L8: Land | M8: High | N8: EU | O8: =Table14[[#This Row],[Profit]]/Table14[[#This Row],[Total_Sales]] -> 0.21235195 | P8: =DATE(YEAR(Table14[[#This Row],[Order_Date]]), MONTH(Table14[[#This Row],[Order_Date]]), 1) -> 45444 | Q8: =_xlfn.XLOOKUP(Table14[[#This Row],[Product]],Product_Master!$B$2:$B$11,Product_Master!$D$2:$D$11) -> ClearCraft | R8: =_xlfn.XLOOKUP(Table14[[#This Row],[Product]],Product_Master!$B$2:$B$11,Product_Master!$E$2:$E$11) -> India | S8: =_xlfn.XLOOKUP(Table14[[#This Row],[Product]],Product_Master!$B$2:$B$11,Product_Master!$F$2:$F$11) -> 22.5
A9: ORD_2025_0008 | B9: May-2025 | C9: Miller, John | D9: China | E9: Cotton Bedsheet | F9: Textiles | G9: 14 | H9: 30.71 | I9: 429.94 | J9: 13.03 | K9: 66.91 | L9: Sea | M9: Low | N9: AS | O9: =Table14[[#This Row],[Profit]]/Table14[[#This Row],[Total_Sales]] -> 0.15562637 | P9: =DATE(YEAR(Table14[[#This Row],[Order_Date]]), MONTH(Table14[[#This Row],[Order_Date]]), 1) -> 45778 | Q9: =_xlfn.XLOOKUP(Table14[[#This Row],[Product]],Product_Master!$B$2:$B$11,Product_Master!$D$2:$D$11) -> SoftWeave | R9: =_xlfn.XLOOKUP(Table14[[#This Row],[Product]],Product_Master!$B$2:$B$11,Product_Master!$E$2:$E$11) -> Turkey | S9: =_xlfn.XLOOKUP(Table14[[#This Row],[Product]],Product_Master!$B$2:$B$11,Product_Master!$F$2:$F$11) -> 25
A10: ORD_2025_0009 | B10: Sep-2024 | C10: Davis, John | D10: Usa | E10: Ceramic Vase | F10: Home Decor | G10: 47 | H10: 24.47 | I10: 1150.09 | J10: 61.3 | K10: 360.29 | L10: Sea | M10: Low | N10: NA | O10: =Table14[[#This Row],[Profit]]/Table14[[#This Row],[Total_Sales]] -> 0.31327114 | P10: =DATE(YEAR(Table14[[#This Row],[Order_Date]]), MONTH(Table14[[#This Row],[Order_Date]]), 1) -> 45536 | Q10: =_xlfn.XLOOKUP(Table14[[#This Row],[Product]],Product_Master!$B$2:$B$11,Product_Master!$D$2:$D$11) -> Artisans Co. | R10: =_xlfn.XLOOKUP(Table14[[#This Row],[Product]],Product_Master!$B$2:$B$11,Product_Master!$E$2:$E$11) -> India | S10: =_xlfn.XLOOKUP(Table14[[#This Row],[Product]],Product_Master!$B$2:$B$11,Product_Master!$F$2:$F$11) -> 15.5
A11: ORD_2025_0010 | B11: Aug-2024 | C11: Martinez, Laura | D11: Italy | E11: LED Lamp | F11: Electronics | G11: 27 | H11: 18.98 | I11: 512.46 | J11: 28.89 | K11: 139.32 | L11: Sea | M11: High | N11: EU | O11: =Table14[[#This Row],[Profit]]/Table14[[#This Row],[Total_Sales]] -> 0.27186512 | P11: =DATE(YEAR(Table14[[#This Row],[Order_Date]]), MONTH(Table14[[#This Row],[Order_Date]]), 1) -> 45505 | Q11: =_xlfn.XLOOKUP(Table14[[#This Row],[Product]],Product_Master!$B$2:$B$11,Product_Master!$D$2:$D$11) -> BrightHome | R11: =_xlfn.XLOOKUP(Table14[[#This Row],[Product]],Product_Master!$B$2:$B$11,Product_Master!$E$2:$E$11) -> Vietnam | S11: =_xlfn.XLOOKUP(Table14[[#This Row],[Product]],Product_Master!$B$2:$B$11,Product_Master!$F$2:$F$11) -> 12.75
A12: ORD_2025_0011 | B12: Apr-2025 | C12: Martinez, James | D12: China | E12: Travel Backpack | F12: Accessories | G12: 32 | H12: 57.84 | I12: 1850.88 | J12: 55.15 | K12: 675.73 | L12: Land | M12: Low | N12: AS | O12: =Table14[[#This Row],[Profit]]/Table14[[#This Row],[Total_Sales]] -> 0.3650858 | P12: =DATE(YEAR(Table14[[#This Row],[Order_Date]]), MONTH(Table14[[#This Row],[Order_Date]]), 1) -> 45748 | Q12: =_xlfn.XLOOKUP(Table14[[#This Row],[Product]],Product_Master!$B$2:$B$11,Product_Master!$D$2:$D$11) -> CarryPro | R12: =_xlfn.XLOOKUP(Table14[[#This Row],[Product]],Product_Master!$B$2:$B$11,Product_Master!$E$2:$E$11) -> Vietnam | S12: =_xlfn.XLOOKUP(Table14[[#This Row],[Product]],Product_Master!$B$2:$B$11,Product_Master!$F$2:$F$11) -> 35
A13: ORD_2025_0012 | B13: Dec-2024 | C13: Davis, James | D13: Canada | E13: Denim Jacket | F13: Apparel | G13: 49 | H13: 58.77 | I13: 2879.73 | J13: 140.29 | K13: 779.44 | L13: Air | M13: High | N13: NA | O13: =Table14[[#This Row],[Profit]]/Table14[[#This Row],[Total_Sales]] -> 0.27066426 | P13: =DATE(YEAR(Table14[[#This Row],[Order_Date]]), MONTH(Table14[[#This Row],[Order_Date]]), 1) -> 45627 | Q13: =_xlfn.XLOOKUP(Table14[[#This Row],[Product]],Product_Master!$B$2:$B$11,Product_Master!$D$2:$D$11) -> BlueWear | R13: =_xlfn.XLOOKUP(Table14[[#This Row],[Product]],Product_Master!$B$2:$B$11,Product_Master!$E$2:$E$11) -> Bangladesh | S13: =_xlfn.XLOOKUP(Table14[[#This Row],[Product]],Product_Master!$B$2:$B$11,Product_Master!$F$2:$F$11) -> 40
... A501: ORD_2025_0500 | B501: Jul-2024 | C501: Hernandez, Michael | D501: Uk | E501: Ceramic Vase | F501: Home Decor | G501: 7 | H501: 24.61 | I501: 172.27 | J501: 9.64 | K501: 54.13 | L501: Air | M501: High | N501: EU | O501: =Table14[[#This Row],[Profit]]/Table14[[#This Row],[Total_Sales]] -> 0.31421606 | P501: =DATE(YEAR(Table14[[#This Row],[Order_Date]]), MONTH(Table14[[#This Row],[Order_Date]]), 1) -> 45474 | Q501: =_xlfn.XLOOKUP(Table14[[#This Row],[Product]],Product_Master!$B$2:$B$11,Product_Master!$D$2:$D$11) -> Artisans Co. | R501: =_xlfn.XLOOKUP(Table14[[#This Row],[Product]],Product_Master!$B$2:$B$11,Product_Master!$E$2:$E$11) -> India | S501: =_xlfn.XLOOKUP(Table14[[#This Row],[Product]],Product_Master!$B$2:$B$11,Product_Master!$F$2:$F$11) -> 15.5

Sheet pivot_Q10
A2: Total Orders | B2: Sum of Total_Sales | C2: Sum of Profit | D2: Average of Profit Margin | E2: Average of Shipping_Cost | F2: Row Labels | G2: Sum of Total_Sales | I2: Row Labels | J2: Sum of Profit
A3: 500 | B3: 474704.62 | C3: 133528.36 | D3: 0.27120316 | E3: 47.21444 | F3: AS | G3: 171168.4 | I3: Denim Jacket | J3: 21393.77
F4: EU | G4: 115214.62 | I4: Travel Backpack | J4: 19312.75
F5: NA | G5: 86945.07 | I5: Table Lamp | J5: 14378.44
F6: OC | G6: 37017.46 | I6: Cotton Bedsheet | J6: 13199.76
F7: SA | G7: 34864.03 | I7: Wireless Mouse | J7: 12566.51
F8: AF | G8: 29495.04 | I8: Ceramic Vase | J8: 12294.77
F9: Grand Total | G9: 474704.62 | I9: Bluetooth Speaker | J9: 11647.44
I10: Leather Wallet | J10: 11364.29
I11: Glass Bowl Set | J11: 9804.13
I12: LED Lamp | J12: 7566.5
I13: Grand Total | J13: 133528.36

Sheet Q10

Sheet Sheet4

Sheet Sheet5
